skeletor/__init__.py
skeletor/datasets.py
skeletor/error.py
skeletor/launcher.py
skeletor/optimizers.py
skeletor/register.py
skeletor/utils.py
skeletor/models/__init__.py
skeletor/models/cv/__init__.py
skeletor/models/cv/densenet.py
skeletor/models/cv/dpn.py
skeletor/models/cv/googlenet.py
skeletor/models/cv/lenet.py
skeletor/models/cv/mobilenet.py
skeletor/models/cv/mobilenetv2.py
skeletor/models/cv/pnasnet.py
skeletor/models/cv/preact_resnet.py
skeletor/models/cv/resnet.py
skeletor/models/cv/resnext.py
skeletor/models/cv/senet.py
skeletor/models/cv/vgg.py
skeletor/proc/__init__.py
skeletor/proc/track_analysis.py
skeletor_ml-0.1.4.dist-info/METADATA
skeletor_ml-0.1.4.dist-info/RECORD
skeletor_ml-0.1.4.dist-info/WHEEL
skeletor_ml-0.1.4.dist-info/top_level.txt
