Metadata-Version: 2.1
Name: skeletor-ml
Version: 0.1.4
Summary: A lightweight module for research experiment reproducibility and analysis
Home-page: https://github.com/noahgolmant/skeletor
Author: Noah Golmant
Author-email: noah.golmant@gmail.com
License: MIT License
Platform: UNKNOWN
Requires-Dist: pyyaml (>=3.12)
Requires-Dist: ray (>=0.4.0)
Requires-Dist: track-ml (>=0.1)
Requires-Dist: torchvision
Requires-Dist: awscli
